simpleprophet/__init__.py
simpleprophet/data.py
simpleprophet/modeling.py
simpleprophet/models.py
simpleprophet/output.py
simpleprophet/pipeline.py
simpleprophet/utils.py
simpleprophet/validations.py
simpleprophet-1.2.dist-info/METADATA
simpleprophet-1.2.dist-info/WHEEL
simpleprophet-1.2.dist-info/top_level.txt
simpleprophet-1.2.dist-info/RECORD
