Metadata-Version: 2.1
Name: simpleprophet
Version: 1.2
Summary: Mozilla simpleprophet forecast framework.
Home-page: https://github.com/mozilla/forecasting
Author: Mozilla
License: UNKNOWN
Platform: UNKNOWN
Classifier: Development Status :: 3 - Alpha
Classifier: Intended Audience :: Developers
Classifier: License :: OSI Approved :: Mozilla Public License 2.0 (MPL 2.0)
Classifier: Programming Language :: Python :: 3
Classifier: Programming Language :: Python :: 3.5
Classifier: Programming Language :: Python :: 3.6
Classifier: Programming Language :: Python :: 3.7
Classifier: Programming Language :: Python :: 3.8
Requires-Python: >=3.5
Requires-Dist: fbprophet (>=0.5)
Requires-Dist: google-cloud-bigquery (>=1.20.0)
Requires-Dist: plotly (>=4.0)
